blueline_client/__init__.py
blueline_client/admin.py
blueline_client/apps.py
blueline_client/models.py
blueline_client/tests.py
blueline_client/utils.py
blueline_client/views.py
blueline_client/migrations/0001_initial.py
blueline_client/migrations/__init__.py
django_blueline_client-0.5.0.dist-info/METADATA
django_blueline_client-0.5.0.dist-info/WHEEL
django_blueline_client-0.5.0.dist-info/top_level.txt
django_blueline_client-0.5.0.dist-info/RECORD
